signalrcore_async/__init__.py
signalrcore_async/helpers.py
signalrcore_async/hub_connection_builder.py
signalrcore_async/messages.py
signalrcore_async/subject.py
signalrcore_async/hub/__init__.py
signalrcore_async/hub/auth_hub_connection.py
signalrcore_async/hub/base_hub_connection.py
signalrcore_async/hub/connection_state.py
signalrcore_async/hub/errors.py
signalrcore_async/hub/reconnection.py
signalrcore_async/protocol/__init__.py
signalrcore_async/protocol/base_hub_protocol.py
signalrcore_async/protocol/json.py
signalrcore_async/protocol/msgpack.py
signalrcore_async-0.5.4.dist-info/LICENSE
signalrcore_async-0.5.4.dist-info/METADATA
signalrcore_async-0.5.4.dist-info/WHEEL
signalrcore_async-0.5.4.dist-info/top_level.txt
signalrcore_async-0.5.4.dist-info/RECORD
