Metadata-Version: 2.1
Name: signalrcore-async
Version: 0.5.4
Summary: Asynchronous fork of signalrcore with MessagePack support: A Python SignalR Core client, with invocation auth and two way streaming. Compatible with azure / serverless functions. Also with automatic reconnect and manual reconnect.
Home-page: https://github.com/apollo3zehn/signalrcore
Author: Apollo3zehn
License: UNKNOWN
Keywords: signalr core client 3.1
Platform: UNKNOWN
Classifier: Programming Language :: Python :: 3
